{
    "app_name": "SCOHAZ12",
    "no_results_found": "dededede",
    "validation_error": "dededede",
    "login_failed": "فشل تسجيل الدخول. يرجى التحقق من بيانات اعتمادك.",
    "invalid_request": "طلب غير صالح",
    "access_denied": "تم رفض الوصول",
    "resource_not_found": "المورد غير موجود",
    "unauthorized": "غير مصرح",
    "forbidden": "ممنوع",
    "page_error": "حدث خطأ في الصفحة",
    "data_error": "خطأ في البيانات. يرجى التحقق من المدخلات والمحاولة مرة أخرى.",
    "missing_field": "هذا الحقل مطلوب.",
    "operation_successful": "تمت العملية بنجاح",
    "changes_saved": "تم حفظ التغييرات.",
    "submission_failed": "فشل الإرسال. يرجى المحاولة مرة أخرى.",
    "form_submission_error": "حدث خطأ أثناء إرسال النموذج",
    "server_maintenance": "الخادم تحت الصيانة. يرجى المحاولة لاحقًا.",
    "action_not_possible": "الإجراء غير ممكن في هذه اللحظة",
    "unknown_error": "حدث خطأ غير معروف.",
    "security": "الأمان",
    "two_factor_authentication": "التحقق الثنائي",
    "enable_2fa": "تفعيل التحقق الثنائي",
    "disable_2fa": "تعطيل التحقق الثنائي",
    "security_settings": "إعدادات الأمان",
    "password_security": "أمان كلمة المرور",
    "change_password": "تغيير كلمة المرور",
    "new_password": "كلمة المرور الجديدة",
    "confirm_password": "تأكيد كلمة المرور",
    "current_password": "كلمة المرور الحالية",
    "password_strength": "قوة كلمة المرور",
    "strong_password_required": "يتطلب الأمر كلمة مرور قوية (على الأقل 8 أحرف، بما في ذلك رقم ورمز خاص)",
    "password_changed_successfully": "تم تغيير كلمة المرور بنجاح.",
    "incorrect_password": "كلمة المرور الحالية غير صحيحة.",
    "password_mismatch": "كلمات المرور غير متطابقة.",
    "password_updated": "تم تحديث كلمة المرور بنجاح.",
    "enable_encryption": "تمكين التشفير",
    "enable_firewall": "تمكين جدار الحماية",
    "firewall_settings": "إعدادات جدار الحماية",
    "account_locked": "تم قفل حسابك بسبب نشاط مشبوه.",
    "account_recovery": "استرداد الحساب",
    "recover_account": "استرداد حسابك",
    "verify_identity": "تحقق من هويتك",
    "password_reset_request": "طلب إعادة تعيين كلمة المرور",
    "password_reset_link_sent": "تم إرسال رابط إعادة تعيين كلمة المرور إلى بريدك الإلكتروني.",
    "password_reset_token_expired": "انتهت صلاحية رمز إعادة تعيين كلمة المرور. يرجى طلب رمز جديد.",
    "confirm_identity": "يرجى تأكيد هويتك للمتابعة.",
    "suspicious_activity_detected": "تم اكتشاف نشاط مشبوه. يرجى مراجعة أفعالك الأخيرة.",
    "login_attempts_exceeded": "تجاوزت عدد محاولات تسجيل الدخول الفاشلة. يرجى المحاولة مرة أخرى بعد بعض الوقت.",
    "multi_factor_authentication": "التحقق متعدد العوامل",
    "enable_multi_factor": "تفعيل التحقق متعدد العوامل",
    "verify_with_sms": "التحقق عبر الرسائل القصيرة",
    "verify_with_email": "التحقق عبر البريد الإلكتروني",
    "app_authenticator": "استخدام تطبيق المصدق",
    "security_question": "سؤال الأمان",
    "answer_security_question": "أجب على سؤال الأمان",
    "account_verification": "التحقق من الحساب",
    "secure_account": "تأمين حسابك",
    "login_security": "أمان تسجيل الدخول",
    "services": "الخدمات",
    "government_services": "الخدمات الحكومية",
    "available_services": "الخدمات المتاحة",
    "service_request": "طلب الخدمة",
    "apply_for_service": "تقديم طلب الخدمة",
    "view_service_status": "عرض حالة الخدمة",
    "service_approved": "تمت الموافقة على الخدمة",
    "service_pending": "الخدمة قيد الانتظار",
    "service_rejected": "تم رفض الخدمة",
    "submit_request": "إرسال الطلب",
    "service_application": "طلب الخدمة",
    "request_received": "تم استلام طلبك",
    "request_in_progress": "طلبك قيد التنفيذ",
    "request_completed": "تم إتمام طلبك",
    "service_request_submitted": "تم تقديم طلب الخدمة",
    "service_under_review": "طلب الخدمة قيد المراجعة",
    "request_approval": "طلب الموافقة",
    "request_status": "حالة الطلب",
    "request_denied": "تم رفض الطلب",
    "service_details": "تفاصيل الخدمة",
    "provide_required_documents": "تقديم الوثائق المطلوبة",
    "attachments_needed": "المرفقات مطلوبة",
    "upload_documents": "رفع الوثائق",
    "submit_documents": "إرسال الوثائق",
    "documents_pending_approval": "الوثائق قيد الموافقة",
    "documents_approved": "تمت الموافقة على الوثائق",
    "documents_rejected": "تم رفض الوثائق",
    "application_pending": "طلبك قيد الانتظار",
    "service_in_progress": "الخدمة قيد التنفيذ",
    "status_updated": "تم تحديث الحالة",
    "status_approved": "تمت الموافقة على الحالة",
    "status_rejected": "تم رفض الحالة",
    "approval_flow": "سير العمل للموافقة",
    "approval_pending": "الموافقة قيد الانتظار",
    "approval_granted": "تم منح الموافقة",
    "approval_denied": "تم رفض الموافقة",
    "workflow_completed": "تم إتمام سير العمل",
    "process_in_progress": "العملية قيد التنفيذ",
    "approval_required": "الموافقة مطلوبة",
    "application_processing": "معالجة الطلب",
    "resubmission_required": "إعادة التقديم مطلوبة",
    "departments": "الأقسام",
    "ministry_of_health": "وزارة الصحة",
    "ministry_of_education": "وزارة التعليم",
    "ministry_of_justice": "وزارة العدل",
    "ministry_of_interior": "وزارة الداخلية",
    "ministry_of_finance": "وزارة المالية",
    "ministry_of_transportation": "وزارة النقل",
    "ministry_of_foreign_affairs": "وزارة الشؤون الخارجية",
    "public_service_department": "إدارة الخدمة العامة",
    "civil_service_department": "إدارة الخدمة المدنية",
    "taxation_department": "إدارة الضرائب",
    "immigration_department": "إدارة الهجرة",
    "department_of_law": "إدارة القانون",
    "department_of_environment": "إدارة البيئة",
    "department_of_culture": "إدارة الثقافة",
    "department_of_economics": "إدارة الاقتصاد",
    "human_resources_department": "إدارة الموارد البشرية",
    "social_security_department": "إدارة الضمان الاجتماعي",
    "public_health_department": "إدارة الصحة العامة",
    "department_of_transport": "إدارة النقل",
    "department_of_veterans_affairs": "إدارة شؤون المحاربين القدامى",
    "department_of_agriculture": "إدارة الزراعة",
    "department_of_housing": "إدارة الإسكان",
    "department_of_energy": "إدارة الطاقة",
    "department_of_communications": "إدارة الاتصالات",
    "department_of_public_safety": "إدارة السلامة العامة",
    "department_of_defense": "إدارة الدفاع",
    "department_of_industrial_relations": "إدارة العلاقات الصناعية",
    "department_of_financial_services": "إدارة الخدمات المالية",
    "workplace": "مكان العمل",
    "human_resources": "الموارد البشرية",
    "employee_details": "تفاصيل الموظف",
    "employee_id": "رقم الموظف",
    "full_name": "الاسم الكامل",
    "email_address": "عنوان البريد الإلكتروني",
    "phone_number": "رقم الهاتف",
    "hire_date": "تاريخ التوظيف",
    "salary": "الراتب",
    "job_title": "المسمى الوظيفي",
    "department": "القسم",
    "supervisor": "المشرف",
    "performance_review": "مراجعة الأداء",
    "leave_request": "طلب إجازة",
    "vacation_leave": "إجازة سنوية",
    "sick_leave": "إجازة مرضية",
    "parental_leave": "إجازة أمومة/أبوة",
    "personal_leave": "إجازة شخصية",
    "leave_balance": "رصيد الإجازة",
    "hours_worked": "عدد الساعات العمل",
    "overtime": "ساعات إضافية",
    "attendance": "الحضور",
    "absence": "الغياب",
    "employee_performance": "أداء الموظف",
    "training_and_development": "التدريب والتطوير",
    "career_growth": "النمو المهني",
    "promotion": "ترقية",
    "job_openings": "فرص العمل",
    "employee_benefits": "مزايا الموظف",
    "health_insurance": "التأمين الصحي",
    "retirement_plan": "خطة التقاعد",
    "employee_wellbeing": "رفاهية الموظف",
    "workplace_safety": "سلامة مكان العمل",
    "incident_report": "تقرير الحادث",
    "accident": "حادث",
    "safety_protocol": "بروتوكول السلامة",
    "workplace_guidelines": "إرشادات مكان العمل",
    "remote_work": "العمل عن بُعد",
    "work_schedule": "جدول العمل",
    "team_meeting": "اجتماع الفريق",
    "project_management": "إدارة المشاريع",
    "project_status": "حالة المشروع",
    "task_management": "إدارة المهام",
    "team_collaboration": "التعاون الفريق",
    "project_deadline": "موعد تسليم المشروع",
    "milestone": "المعالم",
    "project_budget": "ميزانية المشروع",
    "resource_allocation": "تخصيص الموارد",
    "stakeholders": "المعنيون",
    "team_member": "عضو الفريق",
    "team_leader": "قائد الفريق",
    "team_project": "مشروع الفريق",
    "project_plan": "خطة المشروع",
    "project_phases": "مراحل المشروع",
    "project_report": "تقرير المشروع",
    "project_completions": "إكمال المشروع",
    "feedback": "التعليقات",
    "team_feedback": "تعليقات الفريق",
    "performance_feedback": "تعليقات الأداء",
    "client_feedback": "تعليقات العميل",
    "customer_service": "خدمة العملاء",
    "customer_support": "دعم العملاء",
    "client_service": "خدمة العميل",
    "support_ticket": "تذكرة الدعم",
    "resolve_issue": "حل المشكلة",
    "issue_report": "تقرير المشكلة",
    "service_resolution": "حل الخدمة",
    "client_request": "طلب العميل",
    "technical_support": "الدعم الفني",
    "help_center": "مركز المساعدة",
    "user_guides": "دليل المستخدم",
    "troubleshooting": "استكشاف الأخطاء وإصلاحها",
    "knowledge_base": "قاعدة المعرفة",
    "faqs": "الأسئلة المتكررة",
    "how_to_guides": "إرشادات كيفية",
    "live_chat": "الدردشة الحية",
    "email_support": "دعم البريد الإلكتروني",
    "call_support": "دعم الهاتف",
    "support_hours": "ساعات الدعم",
    "support_team": "فريق الدعم",
    "customer_feedback": "تعليقات العملاء",
    "feedback_form": "نموذج التعليقات",
    "service_rating": "تقييم الخدمة",
    "survey": "استطلاع الرأي",
    "customer_satisfaction": "رضا العملاء",
    "product_feedback": "تعليقات المنتج",
    "product_review": "مراجعة المنتج",
    "product_suggestions": "اقتراحات المنتج",
    "service_improvement": "تحسين الخدمة",
    "service_quality": "جودة الخدمة",
    "customer_loyalty": "ولاء العملاء",
    "loyalty_program": "برنامج الولاء",
    "rewards": "المكافآت",
    "discounts": "الخصومات",
    "exclusive_offers": "عروض حصرية",
    "loyalty_points": "نقاط الولاء",
    "referral_program": "برنامج الإحالة",
    "client_referral": "إحالة العميل",
    "refer_a_friend": "أحِل صديقًا",
    "reward_points": "نقاط المكافأة",
    "redeem_rewards": "استبدال المكافآت",
    "customer_reward": "مكافأة العميل",
    "new_user_bonus": "مكافأة المستخدم الجديد",
    "membership": "العضوية",
    "member_discount": "خصم العضو",
    "exclusive_deals": "عروض حصرية",
    "loyalty_benefits": "مزايا الولاء",
    "customer_referral": "إحالة العملاء",
    "social_media": "وسائل التواصل الاجتماعي",
    "facebook": "فيسبوك",
    "twitter": "تويتر",
    "instagram": "إنستغرام",
    "linkedin": "لينكدإن",
    "youtube": "يوتيوب",
    "social_links": "الروابط الاجتماعية",
    "follow_us": "تابعنا",
    "like_us": "أعجبنا",
    "subscribe": "الاشتراك",
    "newsletter": "النشرة الإخبارية",
    "email_subscribe": "الاشتراك عبر البريد الإلكتروني",
    "newsletter_signup": "التسجيل في النشرة الإخبارية",
    "subscribe_newsletter": "اشترك في النشرة الإخبارية",
    "unsubscribe": "إلغاء الاشتراك",
    "email_preference": "تفضيلات البريد الإلكتروني",
    "change_email_preferences": "تغيير تفضيلات البريد الإلكتروني",
    "unsubscribe_from_all": "إلغاء الاشتراك من جميع الرسائل",
    "marketing_emails": "رسائل تسويقية",
    "order_history": "تاريخ الطلبات",
    "track_order": "تتبع الطلب",
    "order_status": "حالة الطلب",
    "order_shipped": "تم شحن الطلب",
    "order_delivered": "تم توصيل الطلب",
    "order_failed": "فشل الطلب",
    "order_pending": "الطلب قيد الانتظار",
    "order_cancelled": "تم إلغاء الطلب",
    "order_returned": "تمت إعادة الطلب",
    "payment_method": "طريقة الدفع",
    "payment_received": "تم استلام الدفع",
    "payment_failed": "فشل الدفع",
    "payment_pending": "الدفع قيد الانتظار",
    "payment_completed": "تم إتمام الدفع",
    "refund_request": "طلب استرداد",
    "refund_status": "حالة الاسترداد",
    "refund_approved": "تمت الموافقة على الاسترداد",
    "refund_rejected": "تم رفض الاسترداد",
    "refund_in_progress": "الاسترداد قيد المعالجة",
    "refunded_amount": "المبلغ المسترد",
    "account_balance": "رصيد الحساب",
    "account_credit": "رصيد الحساب الائتماني",
    "transaction_history": "تاريخ المعاملات",
    "credit_card": "بطاقة الائتمان",
    "debit_card": "بطاقة الخصم",
    "payment_gateway": "بوابة الدفع",
    "paypal": "باي بال",
    "bank_transfer": "التحويل البنكي",
    "transaction_success": "تمت المعاملة بنجاح",
    "transaction_failed": "فشلت المعاملة",
    "card_declined": "تم رفض البطاقة",
    "insufficient_funds": "لا توجد أموال كافية",
    "contact_information": "معلومات الاتصال",
    "update_contact_info": "تحديث معلومات الاتصال",
    "phone_verification": "تحقق من الهاتف",
    "email_verification": "التحقق من البريد الإلكتروني",
    "identity_verification": "التحقق من الهوية",
    "update_profile": "تحديث الملف الشخصي",
    "profile_picture": "الصورة الشخصية",
    "password_reset": "إعادة تعيين كلمة المرور",
    "2fa_disabled": "تم تعطيل التحقق الثنائي",
    "2fa_enabled": "تم تمكين التحقق الثنائي",
    "login_attempts": "محاولات تسجيل الدخول",
    "max_login_attempts": "أقصى عدد لمحاولات تسجيل الدخول",
    "account_suspended": "تم تعليق الحساب",
    "suspicious_activity": "نشاط مريب",
    "reset_password_link": "رابط إعادة تعيين كلمة المرور",
    "password_reset_success": "تم إعادة تعيين كلمة المرور بنجاح",
    "change_email": "تغيير البريد الإلكتروني",
    "update_email": "تحديث البريد الإلكتروني",
    "verify_email": "التحقق من البريد الإلكتروني",
    "verify_phone": "التحقق من الهاتف",
    "account_security": "أمن الحساب",
    "login_history": "سجل تسجيل الدخول",
    "change_security_question": "تغيير سؤال الأمان",
    "security_alert": "تنبيه أمني",
    "unauthorized_access": "الوصول غير المصرح به",
    "logout": "تسجيل الخروج",
    "login_success": "تم تسجيل الدخول بنجاح",
    "session_expired": "انتهت صلاحية الجلسة",
    "login_required": "يتطلب تسجيل الدخول",
    "permission_denied": "تم رفض الإذن",
    "profile_not_found": "الملف الشخصي غير موجود",
    "user_not_found": "المستخدم غير موجود",
    "invalid_credentials": "بيانات الاعتماد غير صحيحة",
    "password_incorrect": "كلمة المرور غير صحيحة",
    "account_creation": "إنشاء الحساب",
    "create_account": "إنشاء حساب",
    "account_exists": "الحساب موجود بالفعل",
    "account_created": "تم إنشاء الحساب بنجاح",
    "registration_success": "تم التسجيل بنجاح",
    "registration_failed": "فشل التسجيل",
    "reset_password": "إعادة تعيين كلمة المرور",
    "forgot_password": "نسيت كلمة المرور",
    "no_account": "ليس لديك حساب؟",
    "terms_of_service": "شروط الخدمة",
    "privacy_policy": "سياسة الخصوصية",
    "accept_terms": "قبول الشروط",
    "disclaimer": "إخلاء المسؤولية",
    "contact_us": "اتصل بنا",
    "about_us": "معلومات عنا",
    "support": "الدعم",
    "faq": "الأسئلة الشائعة",
    "request_support": "طلب الدعم",
    "rate_us": "قيّمنا",
    "app_feedback": "تعليقات التطبيق",
    "error_occurred": "حدث خطأ",
    "success": "نجاح",
    "failure": "فشل",
    "system_error": "خطأ في النظام",
    "maintenance": "الصيانة",
    "under_maintenance": "قيد الصيانة",
    "server_error": "خطأ في الخادم",
    "network_error": "خطأ في الشبكة",
    "retry": "إعادة المحاولة",
    "loading": "جار التحميل",
    "please_wait": "الرجاء الانتظار",
    "processing": "جاري المعالجة",
    "action_failed": "فشل الإجراء",
    "action_successful": "تم الإجراء بنجاح",
    "not_found": "غير موجود",
    "page_not_found": "الصفحة غير موجودة",
    "back_to_home": "العودة إلى الصفحة الرئيسية",
    "contact_form": "نموذج الاتصال",
    "send_message": "إرسال الرسالة",
    "message_sent": "تم إرسال الرسالة",
    "message_failed": "فشل إرسال الرسالة",
    "subscribed": "تم الاشتراك",
    "unsubscribe_newsletter": "إلغاء الاشتراك من النشرة الإخبارية",
    "service_accepted": "تم قبول الخدمة",
    "request_submitted": "تم تقديم الطلب",
    "request_pending": "الطلب قيد الانتظار",
    "request_approved": "تمت الموافقة على الطلب",
    "request_rejected": "تم رفض الطلب",
    "request_failed": "فشل الطلب",
    "pending_approval": "قيد الموافقة",
    "approved": "موافق عليه",
    "rejected": "مرفوض",
    "approved_request": "طلب تم الموافقة عليه",
    "rejected_request": "طلب تم رفضه",
    "in_progress": "قيد التنفيذ",
    "completed": "مكتمل",
    "final_approval": "الموافقة النهائية",
    "cancel_request": "إلغاء الطلب",
    "request_cancelled": "تم إلغاء الطلب",
    "appeal_status": "حالة الاستئناف",
    "appeal_in_progress": "الاستئناف قيد التنفيذ",
    "appeal_decision": "قرار الاستئناف",
    "appeal_approved": "تمت الموافقة على الاستئناف",
    "appeal_rejected": "تم رفض الاستئناف",
    "appeal_failed": "فشل الاستئناف",
    "appeal": "الاستئناف",
    "appeal_status_update": "تحديث حالة الاستئناف",
    "appeal_outcome": "نتيجة الاستئناف",
    "appeal_processing": "الاستئناف قيد المعالجة",
    "appeal_closed": "تم إغلاق الاستئناف",
    "appeal_open": "الاستئناف مفتوح",
    "complaint_status": "حالة الشكوى",
    "complaint_received": "تم استلام الشكوى",
    "complaint_in_progress": "الشكوى قيد المعالجة",
    "complaint_resolved": "تم حل الشكوى",
    "complaint_rejected": "تم رفض الشكوى",
    "complaint_appealed": "تم استئناف الشكوى",
    "complaint_feedback": "تعليقات الشكوى",
    "complaint_feedback_received": "تم استلام تعليقات الشكوى",
    "report_issue": "الإبلاغ عن مشكلة",
    "ticket_number": "رقم التذكرة",
    "ticket_status": "حالة التذكرة",
    "ticket_opened": "تم فتح التذكرة",
    "ticket_closed": "تم إغلاق التذكرة",
    "ticket_in_progress": "التذكرة قيد التنفيذ",
    "ticket_feedback": "تعليقات التذكرة",
    "ticket_assistance": "مساعدة التذكرة",
    "service_report": "تقرير الخدمة",
    "service_completed": "تم إتمام الخدمة",
    "service_cancelled": "تم إلغاء الخدمة",
    "service_reopened": "تم إعادة فتح الخدمة",
    "feedback_submitted": "تم تقديم التعليقات",
    "feedback_received": "تم استلام التعليقات"
}